gadm/__init__.py
gadm/dummy_gadget.py
gadm/gadgetron_dataflow_monitor.py
gadm/multimethod_test.py
gadm/pyside6_and_matplotlib.py
gadm/run_gadgetron_dataflow_monitor_with_ismrmrd_data.py
gadm/visualization_original.py
gadm/test_datas/testdata.h5
gadgetron_dataflow_monitor-0.96.2.dist-info/METADATA
gadgetron_dataflow_monitor-0.96.2.dist-info/WHEEL
gadgetron_dataflow_monitor-0.96.2.dist-info/top_level.txt
gadgetron_dataflow_monitor-0.96.2.dist-info/RECORD
