Metadata-Version: 2.1
Name: gadgetron-dataflow-monitor
Version: 0.96.2
Summary: Gadgetron Dataflow Monitor
Home-page: https://github.com/medlab/gadgetron-dataflow-monitor
Author: Cong Zhang
Author-email: congzhangzh@gmail.com
Maintainer: Cong Zhang
Maintainer-email: congzhangzh@gmail.com
License: UNKNOWN
Platform: UNKNOWN
Classifier: License :: OSI Approved :: MIT License
Classifier: Programming Language :: Python :: 3
Classifier: Operating System :: OS Independent
Requires-Dist: gadgetron
Requires-Dist: matplotlibqml
Requires-Dist: PySide6
